nightskycam_focus/__init__.py
nightskycam_focus/adapter.py
nightskycam_focus/main.py
nightskycam_focus/py.typed
nightskycam_focus-0.1.9.dist-info/METADATA
nightskycam_focus-0.1.9.dist-info/WHEEL
nightskycam_focus-0.1.9.dist-info/entry_points.txt
nightskycam_focus-0.1.9.dist-info/RECORD
