Metadata-Version: 2.4
Name: nightskycam-focus
Version: 0.1.9
Summary: focusing nightskycam zwo-asi cameras
Author: Vincent Berenz
Author-email: vberenz@tuebingen.mpg.de
Requires-Python: >=3.12,<4
Classifier: Programming Language :: Python :: 3
Classifier: Programming Language :: Python :: 3.12
Classifier: Programming Language :: Python :: 3.13
Classifier: Programming Language :: Python :: 3.14
Requires-Dist: astropy (>=7.2.0,<8.0.0)
Requires-Dist: matplotlib (>=3.10.7,<4.0.0)
Requires-Dist: opencv-python (>=4.12.0.88,<5.0.0.0)
Requires-Dist: rpi-gpio (>=0.7.1,<0.8.0)
Requires-Dist: scipy (>=1.16.3,<2.0.0)
Requires-Dist: spidev (>=3.8,<4.0)
